aiohttp_session_ws/__init__.py
aiohttp_session_ws-1.1.1.dist-info/LICENSE
aiohttp_session_ws-1.1.1.dist-info/WHEEL
aiohttp_session_ws-1.1.1.dist-info/METADATA
aiohttp_session_ws-1.1.1.dist-info/RECORD
